{
  "batch": 19,
  "totalBatches": 19,
  "startIndex": 180,
  "count": 5,
  "commits": [
    {
      "sha": "df9676d",
      "fullSha": "df9676df706304299e9ac7bbd042f078fe241251",
      "author_id": "devmade.ai@gmail.com",
      "author": {
        "name": "devmade-ai",
        "email": "devmade.ai@gmail.com"
      },
      "committer": {
        "name": "devmade-ai",
        "email": "devmade.ai@gmail.com"
      },
      "timestamp": "2026-01-20T12:07:15+00:00",
      "commitDate": "2026-01-20T12:07:15+00:00",
      "subject": "chore: process social-ad-creator batch 12 (10 commits)",
      "body": "",
      "tags": ["docs"],
      "complexity": 1,
      "urgency": 2,
      "impact": "internal",
      "scope": null,
      "title": "process social-ad-creator batch 12 (10 commits)",
      "is_conventional": true,
      "has_breaking_change": false,
      "references": [],
      "stats": {
        "filesChanged": 2,
        "additions": 251,
        "deletions": 3
      },
      "files": [
        "processed/social-ad-creator/batches/batch-012.json",
        "processed/social-ad-creator/manifest.json"
      ],
      "repo_id": "repo-tor"
    },
    {
      "sha": "c9fd282",
      "fullSha": "c9fd28232374a945fed0bf1e2715df601934ace7",
      "author_id": "devmade.ai@gmail.com",
      "author": {
        "name": "devmade-ai",
        "email": "devmade.ai@gmail.com"
      },
      "committer": {
        "name": "devmade-ai",
        "email": "devmade.ai@gmail.com"
      },
      "timestamp": "2026-01-20T12:02:02+00:00",
      "commitDate": "2026-01-20T12:02:02+00:00",
      "subject": "chore: process social-ad-creator batch 11 (10 commits)",
      "body": "",
      "tags": ["docs"],
      "complexity": 1,
      "urgency": 2,
      "impact": "internal",
      "scope": null,
      "title": "process social-ad-creator batch 11 (10 commits)",
      "is_conventional": true,
      "has_breaking_change": false,
      "references": [],
      "stats": {
        "filesChanged": 2,
        "additions": 251,
        "deletions": 3
      },
      "files": [
        "processed/social-ad-creator/batches/batch-011.json",
        "processed/social-ad-creator/manifest.json"
      ],
      "repo_id": "repo-tor"
    },
    {
      "sha": "9f9c9d2",
      "fullSha": "9f9c9d267289a8fb4fbc4ecd81d606cf48e49fb1",
      "author_id": "devmade.ai@gmail.com",
      "author": {
        "name": "devmade-ai",
        "email": "devmade.ai@gmail.com"
      },
      "committer": {
        "name": "devmade-ai",
        "email": "devmade.ai@gmail.com"
      },
      "timestamp": "2026-01-20T11:47:36+00:00",
      "commitDate": "2026-01-20T11:47:36+00:00",
      "subject": "chore: process repo-tor batch 17 (2 commits) - repo complete (156 commits)",
      "body": "",
      "tags": ["docs"],
      "complexity": 1,
      "urgency": 2,
      "impact": "internal",
      "scope": null,
      "title": "process repo-tor batch 17 (2 commits) - repo complete (156 commits)",
      "is_conventional": true,
      "has_breaking_change": false,
      "references": [],
      "stats": {
        "filesChanged": 2,
        "additions": 59,
        "deletions": 3
      },
      "files": [
        "processed/repo-tor/batches/batch-017.json",
        "processed/repo-tor/manifest.json"
      ],
      "repo_id": "repo-tor"
    },
    {
      "sha": "b28700f",
      "fullSha": "b28700f1cbf1050edd981e50716732948e23416b",
      "author_id": "devmade.ai@gmail.com",
      "author": {
        "name": "devmade-ai",
        "email": "devmade.ai@gmail.com"
      },
      "committer": {
        "name": "devmade-ai",
        "email": "devmade.ai@gmail.com"
      },
      "timestamp": "2026-01-20T11:45:42+00:00",
      "commitDate": "2026-01-20T11:45:42+00:00",
      "subject": "chore: process repo-tor batch 16 (10 commits)",
      "body": "",
      "tags": ["docs"],
      "complexity": 1,
      "urgency": 2,
      "impact": "internal",
      "scope": null,
      "title": "process repo-tor batch 16 (10 commits)",
      "is_conventional": true,
      "has_breaking_change": false,
      "references": [],
      "stats": {
        "filesChanged": 2,
        "additions": 252,
        "deletions": 4
      },
      "files": [
        "processed/repo-tor/batches/batch-016.json",
        "processed/repo-tor/manifest.json"
      ],
      "repo_id": "repo-tor"
    },
    {
      "sha": "55c55d5",
      "fullSha": "55c55d56f2d588e127ac39277a96ec431b214726",
      "author_id": "devmade.ai@gmail.com",
      "author": {
        "name": "devmade-ai",
        "email": "devmade.ai@gmail.com"
      },
      "committer": {
        "name": "devmade-ai",
        "email": "devmade.ai@gmail.com"
      },
      "timestamp": "2026-01-20T11:33:19+00:00",
      "commitDate": "2026-01-20T11:33:19+00:00",
      "subject": "chore: extract fresh git data (657 commits, 12 new in repo-tor)",
      "body": "",
      "tags": ["config"],
      "complexity": 2,
      "urgency": 2,
      "impact": "internal",
      "scope": null,
      "title": "extract fresh git data (657 commits, 12 new in repo-tor)",
      "is_conventional": true,
      "has_breaking_change": false,
      "references": [],
      "stats": {
        "filesChanged": 18,
        "additions": 27108,
        "deletions": 4172
      },
      "files": [
        "dashboard/commits.json",
        "dashboard/contributors.json",
        "dashboard/data.json",
        "dashboard/files.json",
        "dashboard/metadata.json",
        "dashboard/summary.json",
        "reports/chatty-chart/data.json",
        "reports/chatty-chart/metadata.json",
        "reports/model-pear/data.json",
        "reports/model-pear/metadata.json",
        "reports/repo-tor/commits.json",
        "reports/repo-tor/contributors.json",
        "reports/repo-tor/data.json",
        "reports/repo-tor/files.json",
        "reports/repo-tor/metadata.json",
        "reports/repo-tor/summary.json",
        "reports/social-ad-creator/data.json",
        "reports/social-ad-creator/metadata.json"
      ],
      "repo_id": "repo-tor"
    }
  ]
}
