{
  "sha": "7419234",
  "fullSha": "7419234485b4f7c63acfb89e9b375cf41bd1d185",
  "author_id": "devmade.ai@gmail.com",
  "author": {
    "name": "devmade-ai",
    "email": "devmade.ai@gmail.com"
  },
  "committer": {
    "name": "devmade-ai",
    "email": "devmade.ai@gmail.com"
  },
  "timestamp": "2026-04-21T20:19:15Z",
  "commitDate": "2026-04-21T20:19:15Z",
  "subject": "docs(session): note the cold audit in the handoff summary",
  "body": "Tags: docs, session-handoff\nComplexity: 1\nUrgency: 1\nImpact: internal\nRisk: low\nDebt: neutral\nEpic: message-scheduling\nSemver: patch",
  "tags": [
    "docs"
  ],
  "complexity": 1,
  "risk": "low",
  "debt": "neutral",
  "epic": "message-scheduling",
  "semver": "patch",
  "scope": "session",
  "title": "note the cold audit in the handoff summary",
  "is_conventional": true,
  "has_breaking_change": false,
  "references": [],
  "stats": {
    "filesChanged": 1,
    "additions": 4,
    "deletions": 0
  },
  "files": [
    "docs/SESSION_NOTES.md"
  ],
  "repo_id": "synctone",
  "urgency": 1,
  "impact": "internal"
}