{
  "sha": "c9cc5bd",
  "fullSha": "c9cc5bd150afc15d8144c1ec64c868b68f614643",
  "author_id": "devmade.ai@gmail.com",
  "author": {
    "name": "devmade-ai",
    "email": "devmade.ai@gmail.com"
  },
  "committer": {
    "name": "devmade-ai",
    "email": "devmade.ai@gmail.com"
  },
  "timestamp": "2026-01-21T19:37:17Z",
  "commitDate": "2026-01-21T19:37:17Z",
  "subject": "docs: add documentation update entry to HISTORY.md",
  "body": "",
  "tags": [
    "docs"
  ],
  "complexity": 1,
  "scope": null,
  "title": "add documentation update entry to HISTORY.md",
  "is_conventional": true,
  "has_breaking_change": false,
  "references": [],
  "stats": {
    "filesChanged": 1,
    "additions": 19,
    "deletions": 0
  },
  "files": [
    "docs/HISTORY.md"
  ],
  "repo_id": "synctone",
  "urgency": 2,
  "impact": "internal"
}