{
  "sha": "e318331",
  "author_id": "jacotheron87@gmail.com",
  "author": {
    "name": "jacotheron87",
    "email": "jacotheron87@gmail.com"
  },
  "timestamp": "2025-12-09T13:50:26Z",
  "subject": "homescreen live message update",
  "body": "",
  "tags": [
    "feature"
  ],
  "complexity": 2,
  "has_breaking_change": false,
  "stats": {
    "filesChanged": 1,
    "additions": 23,
    "deletions": 1
  },
  "files": [
    "hooks/useChats.ts"
  ],
  "repo_id": "synctone",
  "urgency": 2,
  "impact": "user-facing"
}